alaska/__init__.py
alaska/example.py
alaska/keyword_tree.py
alaska/model.py
alaska/params.py
alaska/predict_from_model.py
alaska/results.tgz
alaska/state_dict.pth
alaska/utils.py
alaska/weights.pt
alaska/data/comprehensive_dictionary.csv
alaska/data/input.gz
alaska/data/mnem.30000.vocab
alaska/data/mnem.gz
alaska/data/original_lowered.csv
alaska/data/results.tgz
alaska/data/testcase1.las
alaska/data/testcase2.las
alaska/data/testcase3.las
alaska/data/testcase4.gz
alaska/data/.vector_cache/glove.6B.100d.txt
alaska/data/data/comprehensive_dictionary.csv
alaska/data/data/input.gz
alaska/data/data/original_lowered.csv
alaska/data/data/results.tgz
alaska/data/data/testcase1.las
alaska/data/data/testcase2.las
alaska/data/data/testcase3.las
alaska/data/data/testcase4.gz
alaska/tests/test_all.py
alaska-0.0.4.dist-info/LICENSE
alaska-0.0.4.dist-info/METADATA
alaska-0.0.4.dist-info/WHEEL
alaska-0.0.4.dist-info/top_level.txt
alaska-0.0.4.dist-info/RECORD
